README.md
setup.py
snitch_protos/__init__.py
snitch_protos.egg-info/PKG-INFO
snitch_protos.egg-info/SOURCES.txt
snitch_protos.egg-info/dependency_links.txt
snitch_protos.egg-info/top_level.txt
snitch_protos/protos/__init__.py
snitch_protos/protos/shared/__init__.py
snitch_protos/protos/steps/__init__.py